{"ok": 1, "data": {"avatar_guide": [], "userInfo": {"id": 1824398821, "screen_name": "\u5e38\u7a0b", "profile_image_url": "https://tvax3.sinaimg.cn/crop.0.0.1002.1002.180/6cbe1de5ly8gd6crcgy2jj20ru0ruwi6.jpg?KID=imgbed,tva&Expires=1590552902&ssig=1HQ6xkPBwx", "profile_url": "https://m.weibo.cn/u/1824398821?uid=1824398821&luicode=10000011&lfid=1005051824398821", "statuses_count": 2710, "verified": true, "verified_type": 0, "verified_type_ext": 1, "verified_reason": "\u5c0f\u7c73\u96c6\u56e2\u526f\u603b\u88c1 \u5fae\u535aVLOG\u535a\u4e3b", "close_blue_v": false, "description": "Enjoy Life&amp;Works!", "gender": "m", "mbtype": 12, "urank": 48, "mbrank": 7, "follow_me": false, "following": false, "followers_count": 3436548, "follow_count": 174, "cover_image_phone": "https://wx2.sinaimg.cn/crop.0.0.640.640.640/6cbe1de5ly1gazu5ogl53j20u00u04fs.jpg", "avatar_hd": "https://wx3.sinaimg.cn/orj480/6cbe1de5ly8gd6crcgy2jj20ru0ruwi6.jpg", "like": false, "like_me": false, "toolbar_menus": [{"type": "profile_follow", "name": "\u5173\u6ce8", "sub_type": 0, "params": {"uid": 1824398821}, "actionlog": {"act_code": "594", "fid": "2307741824398821", "oid": "1005051824398821", "cardid": "230774_-_WEIBO_INDEX_PROFILE_FOLLOW", "ext": "uid:7371419172|ouid:1824398821|ptype:0|verified_type:0|load_read_level:0|btn_name:\u5173\u6ce8"}}, {"type": "link", "name": "\u804a\u5929", "params": {"scheme": "sinaweibo://messagelist?uid=1824398821&nick=\u5e38\u7a0b&verified_type=0&send_from=user_profile&ext={\"mark\":null}"}, "actionlog": {"act_code": "594", "fid": "2307741824398821", "oid": "messagelist", "cardid": "230774_-_WEIBO_INDEX_PROFILE_CHAT", "ext": "uid:7371419172|ouid:1824398821|ptype:0|verified_type:0|load_read_level:0|btn_name:\u804a\u5929"}, "scheme": "https://m.weibo.cn/msg/chat?uid=1824398821&nick=%E5%B8%B8%E7%A8%8B&verified_type=0&send_from=user_profile&ext=%7B%22mark%22%3Anull%7D&luicode=10000011&lfid=1005051824398821"}, {"type": "toolbar_menu_list", "name": "\u4ed6\u7684\u70ed\u95e8", "params": {"menu_list": [{"type": "link", "name": "\u70ed\u95e8\u5185\u5bb9", "params": {"scheme": "sinaweibo://cardlist?containerid=2310021824398821_-_HOTMBLOG"}, "actionlog": {"act_code": "594", "fid": "2307741824398821", "oid": "2310021824398821_-_HOTMBLOG", "cardid": "230774_-_WEIBO_INDEX_PROFILE_HOTWEIBO", "ext": "uid:7371419172|ouid:1824398821|ptype:0|verified_type:0|load_read_level:0|btn_name:\u70ed\u95e8\u5185\u5bb9"}, "scheme": "https://m.weibo.cn/p/index?containerid=2310021824398821_-_HOTMBLOG&luicode=10000011&lfid=1005051824398821"}]}, "actionlog": {"act_code": "594", "fid": "2307741824398821", "oid": "1005051824398821", "cardid": "230774_-_WEIBO_INDEX_PROFILE_BTN_ALL", "ext": "uid:7371419172|ouid:1824398821|ptype:0|verified_type:0|load_read_level:0|btn_name:\u4ed6\u7684\u70ed\u95e8"}}]}, "fans_scheme": "https://m.weibo.cn/p/index?containerid=231051_-_fans_intimacy_-_1824398821&luicode=10000011&lfid=1005051824398821", "follow_scheme": "https://m.weibo.cn/p/index?containerid=231051_-_followersrecomm_-_1824398821&luicode=10000011&lfid=1005051824398821", "tabsInfo": {"selectedTab": 1, "tabs": [{"id": 1, "tabKey": "profile", "must_show": 1, "hidden": 0, "title": "\u4e3b\u9875", "tab_type": "profile", "containerid": "2302831824398821"}, {"id": 2, "tabKey": "weibo", "must_show": 1, "hidden": 0, "title": "\u5fae\u535a", "tab_type": "weibo", "containerid": "1076031824398821", "apipath": "/profile/statuses", "url": "/index/my"}, {"id": 4, "tabKey": "original_video", "must_show": 0, "hidden": 0, "title": "\u89c6\u9891", "tab_type": "video", "containerid": "2315671824398821"}, {"id": 10, "tabKey": "album", "must_show": 0, "hidden": 0, "title": "\u76f8\u518c", "tab_type": "album", "containerid": "1078031824398821", "filter_group": [{"name": "\u56fe\u7247\u5899", "containerid": "1078031824398821", "title": "\u56fe\u7247\u5899", "scheme": ""}, {"name": "\u5934\u50cf\u4e13\u8f91", "containerid": "1078031824398821_500341880000001824398821_-_albumeachCard", "title": "\u5934\u50cf\u4e13\u8f91", "scheme": ""}, {"name": "\u9762\u5b54\u4e13\u8f91", "containerid": "1078031824398821_38183471215603580000001824398821_-_albumfaceCard", "title": "\u9762\u5b54\u4e13\u8f91", "scheme": ""}, {"name": "\u76f8\u518c\u4e13\u8f91", "containerid": "1078031824398821_-_albumlist", "title": "\u76f8\u518c\u4e13\u8f91", "scheme": ""}], "filter_group_info": {"title": "\u5168\u90e8\u7167\u7247(5408)", "icon": "http://u1.sinaimg.cn/upload/2014/06/10/userinfo_icon_album.png", "icon_name": "\u4e13\u8f91", "icon_scheme": ""}}]}, "scheme": "sinaweibo://userinfo?uid=1824398821&v_p=42&luicode=10000011&lfid=1005051824398821", "showAppTips": 1}}