{"ok": 1, "data": {"avatar_guide": [], "userInfo": {"id": 2516593910, "screen_name": "\u5c0f\u6069\u7231", "profile_image_url": "https://tvax2.sinaimg.cn/crop.0.0.512.512.180/96002cf6ly8gdj6kbnuc1j20e80e8jrd.jpg?KID=imgbed,tva&Expires=1590554902&ssig=bYUOUfJdwu", "profile_url": "https://m.weibo.cn/u/2516593910?uid=2516593910&luicode=10000011&lfid=1005052516593910", "statuses_count": 6131, "verified": true, "verified_type": 2, "verified_type_ext": 50, "verified_reason": "\u5c0f\u6069\u7231\uff08xiaoenai.com\uff09\u5b98\u65b9\u5fae\u535a", "close_blue_v": false, "description": "\u5c0f\u6069\u7231\u662f\u60c5\u4fa3\u5fc5\u5907\u5e94\u7528\u4ea7\u54c1\u3002\u901a\u8fc7\u5c0f\u6069\u7231\uff0c\u60c5\u4fa3\u95f4\u7684\u6c9f\u901a\u66f4\u6709\u4e50\u8da3\uff0c\u4e30\u5bcc\u4e8c\u4eba\u751f\u6d3b\u3002\u5b98\u7f51\uff1ahttp://xiaoenai.com \u5fae\u4fe1\u516c\u4f17\u53f7\uff1a\u5c0f\u6069\u7231", "gender": "f", "mbtype": 11, "urank": 46, "mbrank": 3, "follow_me": false, "following": false, "followers_count": 1225574, "follow_count": 94, "cover_image_phone": "https://tva4.sinaimg.cn/crop.0.0.0.0/96002cf6jw1em0isp53c6j20qo0qoq7q.jpg", "avatar_hd": "https://wx2.sinaimg.cn/orj480/96002cf6ly8gdj6kbnuc1j20e80e8jrd.jpg", "like": false, "like_me": false, "toolbar_menus": [{"type": "profile_follow", "name": "\u5173\u6ce8", "pic": "", "params": {"uid": 2516593910}}, {"type": "link", "name": "\u804a\u5929", "pic": "http://h5.sinaimg.cn/upload/2015/06/12/2/toolbar_icon_discuss_default.png", "params": {"scheme": "sinaweibo://messagelist?uid=2516593910&nick=\u5c0f\u6069\u7231"}, "scheme": "https://m.weibo.cn/msg/chat?uid=2516593910&nick=%E5%B0%8F%E6%81%A9%E7%88%B1&luicode=10000011&lfid=1005052516593910"}, {"type": "link", "name": "\u6587\u7ae0", "pic": "", "params": {"scheme": "sinaweibo://cardlist?containerid=2303190002_445_2516593910_WEIBO_ARTICLE_LIST_DETAIL&count=20"}, "scheme": "https://m.weibo.cn/p/index?containerid=2303190002_445_2516593910_WEIBO_ARTICLE_LIST_DETAIL&count=20&luicode=10000011&lfid=1005052516593910"}]}, "fans_scheme": "https://m.weibo.cn/p/index?containerid=231051_-_fans_intimacy_-_2516593910&luicode=10000011&lfid=1005052516593910", "follow_scheme": "https://m.weibo.cn/p/index?containerid=231051_-_followersrecomm_-_2516593910&luicode=10000011&lfid=1005052516593910", "tabsInfo": {"selectedTab": 1, "tabs": [{"id": 1, "tabKey": "profile", "must_show": 1, "hidden": 0, "title": "\u4e3b\u9875", "tab_type": "profile", "containerid": "2302832516593910"}, {"id": 2, "tabKey": "weibo", "must_show": 1, "hidden": 0, "title": "\u5fae\u535a", "tab_type": "weibo", "containerid": "1076032516593910", "apipath": "/profile/statuses", "url": "/index/my"}, {"id": 4, "tabKey": "original_video", "must_show": 0, "hidden": 0, "title": "\u89c6\u9891", "tab_type": "video", "containerid": "2315672516593910"}, {"id": 10, "tabKey": "album", "must_show": 0, "hidden": 0, "title": "\u76f8\u518c", "tab_type": "album", "containerid": "1078032516593910", "filter_group": [{"name": "\u56fe\u7247\u5899", "containerid": "1078032516593910", "title": "\u56fe\u7247\u5899", "scheme": ""}, {"name": "\u5934\u50cf\u4e13\u8f91", "containerid": "1078032516593910_331842260000002516593910_-_albumeachCard", "title": "\u5934\u50cf\u4e13\u8f91", "scheme": ""}, {"name": "\u76f8\u518c\u4e13\u8f91", "containerid": "1078032516593910_-_albumlist", "title": "\u76f8\u518c\u4e13\u8f91", "scheme": ""}], "filter_group_info": {"title": "\u5168\u90e8\u7167\u7247(18999)", "icon": "http://u1.sinaimg.cn/upload/2014/06/10/userinfo_icon_album.png", "icon_name": "\u4e13\u8f91", "icon_scheme": ""}}]}, "scheme": "sinaweibo://userinfo?uid=2516593910&v_p=42&luicode=10000011&lfid=1005052516593910", "showAppTips": 1}}